openapi_core/__init__.py
openapi_core/app.py
openapi_core/casting/__init__.py
openapi_core/casting/schemas/__init__.py
openapi_core/casting/schemas/casters.py
openapi_core/casting/schemas/datatypes.py
openapi_core/casting/schemas/exceptions.py
openapi_core/casting/schemas/factories.py
openapi_core/configurations.py
openapi_core/contrib/__init__.py
openapi_core/contrib/aiohttp/__init__.py
openapi_core/contrib/aiohttp/requests.py
openapi_core/contrib/aiohttp/responses.py
openapi_core/contrib/django/__init__.py
openapi_core/contrib/django/decorators.py
openapi_core/contrib/django/handlers.py
openapi_core/contrib/django/integrations.py
openapi_core/contrib/django/middlewares.py
openapi_core/contrib/django/providers.py
openapi_core/contrib/django/requests.py
openapi_core/contrib/django/responses.py
openapi_core/contrib/falcon/__init__.py
openapi_core/contrib/falcon/handlers.py
openapi_core/contrib/falcon/integrations.py
openapi_core/contrib/falcon/middlewares.py
openapi_core/contrib/falcon/requests.py
openapi_core/contrib/falcon/responses.py
openapi_core/contrib/falcon/util.py
openapi_core/contrib/falcon/views.py
openapi_core/contrib/fastapi/__init__.py
openapi_core/contrib/fastapi/middlewares.py
openapi_core/contrib/fastapi/requests.py
openapi_core/contrib/fastapi/responses.py
openapi_core/contrib/flask/__init__.py
openapi_core/contrib/flask/decorators.py
openapi_core/contrib/flask/handlers.py
openapi_core/contrib/flask/integrations.py
openapi_core/contrib/flask/providers.py
openapi_core/contrib/flask/requests.py
openapi_core/contrib/flask/responses.py
openapi_core/contrib/flask/views.py
openapi_core/contrib/requests/__init__.py
openapi_core/contrib/requests/protocols.py
openapi_core/contrib/requests/requests.py
openapi_core/contrib/requests/responses.py
openapi_core/contrib/starlette/__init__.py
openapi_core/contrib/starlette/handlers.py
openapi_core/contrib/starlette/integrations.py
openapi_core/contrib/starlette/middlewares.py
openapi_core-0.21.0.dist-info/METADATA
openapi_core-0.21.0.dist-info/WHEEL
openapi_core-0.21.0.dist-info/licenses/LICENSE
openapi_core-0.21.0.dist-info/RECORD
